{
  "name": "Hindi Traditional",
  "keys": {
    "E01": {
      "to": "1",
      "shift": "ऍ",
      "caps+shift": "ऍ",
      "altR+caps? ctrl+alt+caps?": "१",
      "altR+shift+caps? ctrl+alt+shift+caps?": "!",
      "ctrl+shift+caps?": "&#x200D;"
    },
    "E02": {
      "to": "2",
      "shift": "&#x945;",
      "caps+shift": "&#x945;",
      "altR+caps? ctrl+alt+caps?": "२",
      "altR+shift+caps? ctrl+alt+shift+caps?": "@",
      "ctrl+shift+caps?": "&#x200C;"
    },
    "E03": {
      "to": "3",
      "shift": "&#x94D;र",
      "altR+caps? ctrl+alt+caps?": "३",
      "altR+shift+caps? ctrl+alt+shift+caps?": "#"
    },
    "E04": {
      "to": "4",
      "shift": "र&#x94D;",
      "altR+caps? ctrl+alt+caps?": "४",
      "altR+shift+caps? ctrl+alt+shift+caps?": "$",
      "ctrl+shift+caps?": "₹"
    },
    "E05": {
      "to": "5",
      "shift": "ज&#x94D;ञ",
      "altR+caps? ctrl+alt+caps?": "५",
      "altR+shift+caps? ctrl+alt+shift+caps?": "%"
    },
    "E06": {
      "to": "6",
      "shift": "त&#x94D;र",
      "altR+caps? ctrl+alt+caps?": "६",
      "altR+shift+caps? ctrl+alt+shift+caps?": "^"
    },
    "E07": {
      "to": "7",
      "shift": "क&#x94D;ष",
      "altR+caps? ctrl+alt+caps?": "७",
      "altR+shift+caps? ctrl+alt+shift+caps?": "&"
    },
    "E08": {
      "to": "8",
      "shift": "श&#x94D;र",
      "altR+caps? ctrl+alt+caps?": "८",
      "altR+shift+caps? ctrl+alt+shift+caps?": "*"
    },
    "E09": {
      "to": "9",
      "shift": "(",
      "caps+shift": "(",
      "altR+caps? ctrl+alt+caps?": "९",
      "altR+shift+caps? ctrl+alt+shift+caps?": "("
    },
    "E10": {
      "to": "0",
      "shift": ")",
      "caps+shift": ")",
      "altR+caps? ctrl+alt+caps?": "०",
      "altR+shift+caps? ctrl+alt+shift+caps?": ")"
    },
    "E11": {
      "to": "-",
      "shift": "&#x903;",
      "caps+shift": "&#x903;",
      "altR+caps? ctrl+alt+caps?": "-",
      "altR+shift+caps? ctrl+alt+shift+caps?": "_"
    },
    "E12": {
      "to": "&#x943;",
      "shift": "ऋ",
      "caps+shift": "ऋ",
      "altR+caps? ctrl+alt+caps?": "=",
      "altR+shift+caps? ctrl+alt+shift+caps?": "+"
    },
    "D01": {
      "to": "&#x94C;",
      "shift": "औ",
      "caps+shift": "औ"
    },
    "D02": {
      "to": "&#x948;",
      "shift": "ऐ",
      "caps+shift": "ऐ"
    },
    "D03": {
      "to": "&#x93E;",
      "shift": "आ",
      "caps+shift": "आ"
    },
    "D04": {
      "to": "&#x940;",
      "shift": "ई",
      "caps+shift": "ई"
    },
    "D05": {
      "to": "&#x942;",
      "shift": "ऊ",
      "caps+shift": "ऊ"
    },
    "D06": {
      "to": "ब",
      "shift": "भ",
      "caps+shift": "भ"
    },
    "D07": {
      "to": "ह",
      "shift": "ङ",
      "caps+shift": "ङ"
    },
    "D08": {
      "to": "ग",
      "shift": "घ",
      "caps+shift": "घ"
    },
    "D09": {
      "to": "द",
      "shift": "ध",
      "caps+shift": "ध"
    },
    "D10": {
      "to": "ज",
      "shift": "झ",
      "caps+shift": "झ"
    },
    "D11": {
      "to": "ड",
      "shift": "ढ",
      "caps+shift": "ढ",
      "altR+caps? ctrl+alt+caps?": "[",
      "altR+shift+caps? ctrl+alt+shift+caps?": "{"
    },
    "D12": {
      "to": "&#x93C;",
      "shift": "ञ",
      "caps+shift": "ञ",
      "altR+caps? ctrl+alt+caps?": "]",
      "altR+shift+caps? ctrl+alt+shift+caps?": "}"
    },
    "C01": {
      "to": "&#x94B;",
      "shift": "ओ",
      "caps+shift": "ओ"
    },
    "C02": {
      "to": "&#x947;",
      "shift": "ए",
      "caps+shift": "ए"
    },
    "C03": {
      "to": "&#x94D;",
      "shift": "अ",
      "caps+shift": "अ"
    },
    "C04": {
      "to": "&#x93F;",
      "shift": "इ",
      "caps+shift": "इ"
    },
    "C05": {
      "to": "&#x941;",
      "shift": "उ",
      "caps+shift": "उ"
    },
    "C06": {
      "to": "प",
      "shift": "फ",
      "caps+shift": "फ"
    },
    "C07": {
      "to": "र",
      "shift": "ऱ",
      "caps+shift": "ऱ"
    },
    "C08": {
      "to": "क",
      "shift": "ख",
      "caps+shift": "ख"
    },
    "C09": {
      "to": "त",
      "shift": "थ",
      "caps+shift": "थ"
    },
    "C10": {
      "to": "च",
      "shift": "छ",
      "caps+shift": "छ",
      "altR+caps? ctrl+alt+caps?": ";",
      "altR+shift+caps? ctrl+alt+shift+caps?": ":"
    },
    "C11": {
      "to": "ट",
      "shift": "ठ",
      "caps+shift": "ठ",
      "altR+caps? ctrl+alt+caps?": "'",
      "altR+shift+caps? ctrl+alt+shift+caps?": "&#x22;"
    },
    "C12": {
      "to": "&#x949;",
      "shift": "ऑ",
      "caps+shift": "ऑ",
      "altR+caps? ctrl+alt+caps?": "\\",
      "altR+shift+caps? ctrl+alt+shift+caps?": "|"
    },
    "B00": {
      "to": "&#x949;",
      "shift": "ऑ",
      "caps+shift": "ऑ"
    },
    "B02": {
      "to": "&#x902;",
      "shift": "&#x901;",
      "caps+shift": "&#x901;",
      "altR+shift+caps? ctrl+alt+shift+caps?": "ॐ"
    },
    "B03": {
      "to": "म",
      "shift": "ण",
      "caps+shift": "ण"
    },
    "B04": {
      "to": "न"
    },
    "B05": {
      "to": "व"
    },
    "B06": {
      "to": "ल",
      "shift": "ळ",
      "caps+shift": "ळ"
    },
    "B07": {
      "to": "स",
      "shift": "श",
      "caps+shift": "श"
    },
    "B08": {
      "to": ",",
      "shift": "ष",
      "caps+shift": "ष",
      "altR+caps? ctrl+alt+caps?": ",",
      "altR+shift+caps? ctrl+alt+shift+caps?": "<"
    },
    "B09": {
      "to": ".",
      "shift": "।",
      "caps+shift": "।",
      "altR+caps? ctrl+alt+caps?": ".",
      "altR+shift+caps? ctrl+alt+shift+caps?": ">"
    },
    "B10": {
      "to": "य",
      "shift": "य़",
      "caps+shift": "य़",
      "altR+caps? ctrl+alt+caps?": "/",
      "altR+shift+caps? ctrl+alt+shift+caps?": "?"
    },
    "A03": {
      "to": " ",
      "shift": " ",
      "caps+shift": " ",
      "ctrl+caps?": " "
    },
    "E00": {
      "altR+caps? ctrl+alt+caps?": "`",
      "altR+shift+caps? ctrl+alt+shift+caps?": "~"
    }
  },
  "levels": [
    "to",
    "shift",
    "caps+shift",
    "altR+caps? ctrl+alt+caps?",
    "altR+shift+caps? ctrl+alt+shift+caps?",
    "ctrl+caps?",
    "ctrl+shift+caps?"
  ],
  "charMap": {
    "0": [
      "E10",
      "to"
    ],
    "1": [
      "E01",
      "to"
    ],
    "2": [
      "E02",
      "to"
    ],
    "3": [
      "E03",
      "to"
    ],
    "4": [
      "E04",
      "to"
    ],
    "5": [
      "E05",
      "to"
    ],
    "6": [
      "E06",
      "to"
    ],
    "7": [
      "E07",
      "to"
    ],
    "8": [
      "E08",
      "to"
    ],
    "9": [
      "E09",
      "to"
    ],
    "-": [
      "E11",
      "to"
    ],
    "&#x943;": [
      "E12",
      "to"
    ],
    "&#x94C;": [
      "D01",
      "to"
    ],
    "&#x948;": [
      "D02",
      "to"
    ],
    "&#x93E;": [
      "D03",
      "to"
    ],
    "&#x940;": [
      "D04",
      "to"
    ],
    "&#x942;": [
      "D05",
      "to"
    ],
    "ब": [
      "D06",
      "to"
    ],
    "ह": [
      "D07",
      "to"
    ],
    "ग": [
      "D08",
      "to"
    ],
    "द": [
      "D09",
      "to"
    ],
    "ज": [
      "D10",
      "to"
    ],
    "ड": [
      "D11",
      "to"
    ],
    "&#x93C;": [
      "D12",
      "to"
    ],
    "&#x94B;": [
      "C01",
      "to"
    ],
    "&#x947;": [
      "C02",
      "to"
    ],
    "&#x94D;": [
      "C03",
      "to"
    ],
    "&#x93F;": [
      "C04",
      "to"
    ],
    "&#x941;": [
      "C05",
      "to"
    ],
    "प": [
      "C06",
      "to"
    ],
    "र": [
      "C07",
      "to"
    ],
    "क": [
      "C08",
      "to"
    ],
    "त": [
      "C09",
      "to"
    ],
    "च": [
      "C10",
      "to"
    ],
    "ट": [
      "C11",
      "to"
    ],
    "&#x949;": [
      "C12",
      "to"
    ],
    "&#x902;": [
      "B02",
      "to"
    ],
    "म": [
      "B03",
      "to"
    ],
    "न": [
      "B04",
      "to"
    ],
    "व": [
      "B05",
      "to"
    ],
    "ल": [
      "B06",
      "to"
    ],
    "स": [
      "B07",
      "to"
    ],
    ",": [
      "B08",
      "to"
    ],
    ".": [
      "B09",
      "to"
    ],
    "य": [
      "B10",
      "to"
    ],
    " ": [
      "A03",
      "to"
    ],
    "ऍ": [
      "E01",
      "shift"
    ],
    "&#x945;": [
      "E02",
      "shift"
    ],
    "&#x94D;र": [
      "E03",
      "shift"
    ],
    "र&#x94D;": [
      "E04",
      "shift"
    ],
    "ज&#x94D;ञ": [
      "E05",
      "shift"
    ],
    "त&#x94D;र": [
      "E06",
      "shift"
    ],
    "क&#x94D;ष": [
      "E07",
      "shift"
    ],
    "श&#x94D;र": [
      "E08",
      "shift"
    ],
    "(": [
      "E09",
      "shift"
    ],
    ")": [
      "E10",
      "shift"
    ],
    "&#x903;": [
      "E11",
      "shift"
    ],
    "ऋ": [
      "E12",
      "shift"
    ],
    "औ": [
      "D01",
      "shift"
    ],
    "ऐ": [
      "D02",
      "shift"
    ],
    "आ": [
      "D03",
      "shift"
    ],
    "ई": [
      "D04",
      "shift"
    ],
    "ऊ": [
      "D05",
      "shift"
    ],
    "भ": [
      "D06",
      "shift"
    ],
    "ङ": [
      "D07",
      "shift"
    ],
    "घ": [
      "D08",
      "shift"
    ],
    "ध": [
      "D09",
      "shift"
    ],
    "झ": [
      "D10",
      "shift"
    ],
    "ढ": [
      "D11",
      "shift"
    ],
    "ञ": [
      "D12",
      "shift"
    ],
    "ओ": [
      "C01",
      "shift"
    ],
    "ए": [
      "C02",
      "shift"
    ],
    "अ": [
      "C03",
      "shift"
    ],
    "इ": [
      "C04",
      "shift"
    ],
    "उ": [
      "C05",
      "shift"
    ],
    "फ": [
      "C06",
      "shift"
    ],
    "ऱ": [
      "C07",
      "shift"
    ],
    "ख": [
      "C08",
      "shift"
    ],
    "थ": [
      "C09",
      "shift"
    ],
    "छ": [
      "C10",
      "shift"
    ],
    "ठ": [
      "C11",
      "shift"
    ],
    "ऑ": [
      "C12",
      "shift"
    ],
    "&#x901;": [
      "B02",
      "shift"
    ],
    "ण": [
      "B03",
      "shift"
    ],
    "ळ": [
      "B06",
      "shift"
    ],
    "श": [
      "B07",
      "shift"
    ],
    "ष": [
      "B08",
      "shift"
    ],
    "।": [
      "B09",
      "shift"
    ],
    "य़": [
      "B10",
      "shift"
    ],
    "`": [
      "E00",
      "altR+caps? ctrl+alt+caps?"
    ],
    "१": [
      "E01",
      "altR+caps? ctrl+alt+caps?"
    ],
    "२": [
      "E02",
      "altR+caps? ctrl+alt+caps?"
    ],
    "३": [
      "E03",
      "altR+caps? ctrl+alt+caps?"
    ],
    "४": [
      "E04",
      "altR+caps? ctrl+alt+caps?"
    ],
    "५": [
      "E05",
      "altR+caps? ctrl+alt+caps?"
    ],
    "६": [
      "E06",
      "altR+caps? ctrl+alt+caps?"
    ],
    "७": [
      "E07",
      "altR+caps? ctrl+alt+caps?"
    ],
    "८": [
      "E08",
      "altR+caps? ctrl+alt+caps?"
    ],
    "९": [
      "E09",
      "altR+caps? ctrl+alt+caps?"
    ],
    "०": [
      "E10",
      "altR+caps? ctrl+alt+caps?"
    ],
    "=": [
      "E12",
      "altR+caps? ctrl+alt+caps?"
    ],
    "[": [
      "D11",
      "altR+caps? ctrl+alt+caps?"
    ],
    "]": [
      "D12",
      "altR+caps? ctrl+alt+caps?"
    ],
    ";": [
      "C10",
      "altR+caps? ctrl+alt+caps?"
    ],
    "'": [
      "C11",
      "altR+caps? ctrl+alt+caps?"
    ],
    "\\": [
      "C12",
      "altR+caps? ctrl+alt+caps?"
    ],
    "/": [
      "B10",
      "altR+caps? ctrl+alt+caps?"
    ],
    "~": [
      "E00",
      "altR+shift+caps? ctrl+alt+shift+caps?"
    ],
    "!": [
      "E01",
      "altR+shift+caps? ctrl+alt+shift+caps?"
    ],
    "@": [
      "E02",
      "altR+shift+caps? ctrl+alt+shift+caps?"
    ],
    "#": [
      "E03",
      "altR+shift+caps? ctrl+alt+shift+caps?"
    ],
    "$": [
      "E04",
      "altR+shift+caps? ctrl+alt+shift+caps?"
    ],
    "%": [
      "E05",
      "altR+shift+caps? ctrl+alt+shift+caps?"
    ],
    "^": [
      "E06",
      "altR+shift+caps? ctrl+alt+shift+caps?"
    ],
    "&": [
      "E07",
      "altR+shift+caps? ctrl+alt+shift+caps?"
    ],
    "*": [
      "E08",
      "altR+shift+caps? ctrl+alt+shift+caps?"
    ],
    "_": [
      "E11",
      "altR+shift+caps? ctrl+alt+shift+caps?"
    ],
    "+": [
      "E12",
      "altR+shift+caps? ctrl+alt+shift+caps?"
    ],
    "{": [
      "D11",
      "altR+shift+caps? ctrl+alt+shift+caps?"
    ],
    "}": [
      "D12",
      "altR+shift+caps? ctrl+alt+shift+caps?"
    ],
    ":": [
      "C10",
      "altR+shift+caps? ctrl+alt+shift+caps?"
    ],
    "&#x22;": [
      "C11",
      "altR+shift+caps? ctrl+alt+shift+caps?"
    ],
    "|": [
      "C12",
      "altR+shift+caps? ctrl+alt+shift+caps?"
    ],
    "ॐ": [
      "B02",
      "altR+shift+caps? ctrl+alt+shift+caps?"
    ],
    "<": [
      "B08",
      "altR+shift+caps? ctrl+alt+shift+caps?"
    ],
    ">": [
      "B09",
      "altR+shift+caps? ctrl+alt+shift+caps?"
    ],
    "?": [
      "B10",
      "altR+shift+caps? ctrl+alt+shift+caps?"
    ],
    "&#x200D;": [
      "E01",
      "ctrl+shift+caps?"
    ],
    "&#x200C;": [
      "E02",
      "ctrl+shift+caps?"
    ],
    "₹": [
      "E04",
      "ctrl+shift+caps?"
    ]
  },
  "allChars": [
    " ",
    "_",
    "-",
    ",",
    ";",
    ":",
    "!",
    "?",
    ".",
    "।",
    "'",
    "(",
    ")",
    "[",
    "]",
    "{",
    "}",
    "@",
    "*",
    "/",
    "\\",
    "&",
    "&#x200C;",
    "&#x200D;",
    "&#x22;",
    "&#x901;",
    "&#x902;",
    "&#x903;",
    "&#x93C;",
    "&#x93E;",
    "&#x93F;",
    "&#x940;",
    "&#x941;",
    "&#x942;",
    "&#x943;",
    "&#x945;",
    "&#x947;",
    "&#x948;",
    "&#x949;",
    "&#x94B;",
    "&#x94C;",
    "&#x94D;",
    "&#x94D;र",
    "#",
    "%",
    "`",
    "^",
    "+",
    "<",
    "=",
    ">",
    "|",
    "~",
    "$",
    "₹",
    "0",
    "०",
    "1",
    "१",
    "2",
    "२",
    "3",
    "३",
    "4",
    "४",
    "५",
    "5",
    "6",
    "६",
    "७",
    "7",
    "८",
    "8",
    "9",
    "९",
    "ॐ",
    "अ",
    "आ",
    "इ",
    "ई",
    "उ",
    "ऊ",
    "ऋ",
    "ऍ",
    "ए",
    "ऐ",
    "ऑ",
    "ओ",
    "औ",
    "क",
    "क&#x94D;ष",
    "ख",
    "ग",
    "घ",
    "ङ",
    "च",
    "छ",
    "ज",
    "ज&#x94D;ञ",
    "झ",
    "ञ",
    "ट",
    "ठ",
    "ड",
    "ढ",
    "ण",
    "त",
    "त&#x94D;र",
    "थ",
    "द",
    "ध",
    "न",
    "प",
    "फ",
    "ब",
    "भ",
    "म",
    "य",
    "य़",
    "र",
    "ऱ",
    "र&#x94D;",
    "ल",
    "ळ",
    "व",
    "श",
    "श&#x94D;र",
    "ष",
    "स",
    "ह"
  ],
  "enterVariant": 1,
  "enterIso": "C12",
  "settings": {
    "fallback": "omit"
  }
}