{
    "site.title": "اپلیکیشن آنلاین تایپ رایتر",
    "site.description": "تمرینهای مجانی آنلاین! روش تایپ صحیح را بیاموزید٬ مهارت و سرعت تایپ خود را افزایش دهید.",
    "site.navigation.home": "خانه",
    "site.navigation.program": "اپلیکیشن تایپ رایتر",
    "site.navigation.statistics": "آمار",
    "typewriter.page.title": "اپلیکیشن تایپ رایتر",
    "404.page.title": "یافت نشد",
    "404.page.desc": "صفحه مورد نطر یافت نشد",
    "error.not.found.character.on.keyboard": "حرف در صفحه کلید پیدا نشد",
    "site.version": "{version} :نسخه",
    "site.copyright": "تمامی حقوق محفوظ می باشد",
    "site.customerSupport": "خدمات مشتری",
    "site.legalNotice": "اطلاعیه قانونی",
    "site.termsOfUse": "شرایط استفاده",
    "site.privacyPolicy": "سیاست حفظ حریم خصوصی",
    "site.contactInfo": "اطلاعات تماس",
    "site.email": "پست الکترونیک",
    "site.about": "درباره",
    "site.navigation.settings": "تنظیمات",
    "general.ok": "تأیید",
    "general.cancel": "لغو",
    "general.error.title": "خطا",
    "site.languageNameOnNativeLanguage": "فارسی",
    "site.keywords.online": "آنلاین",
    "site.keywords.instructor": "اموزگار",
    "site.keywords.tutor": "مربی",
    "site.keywords.tutorial": "آموزش",
    "site.keywords.education": "تحصیلات",
    "site.keywords.teaching": "درس دادن",
    "site.keywords.learning": "یادگیری",
    "site.keywords.application": "درخواست",
    "site.keywords.typewriting": "",
    "site.keywords.typewriter": "",
    "site.keywords.type": "تایپ",
    "site.keywords.typing": "تایپ کردن",
    "site.keywords.10Thumbs": "ده انگشت",
    "site.keywords.tenFinger": "ده انگشت",
    "site.keywords.lessons": "درسها",
    "site.keywords.practices": "تمرینات",
    "site.keywords.course": "دوره",
    "site.underDevelopement": "در حال توسعه",
    "site.warning.mobile": "به نظر می رسد شما از یک دستگاه تلفن همراه استفاده می کنید. این برنامه فقط روی رایانه کار می کند. برای یادگیری تایپ با ده انگشت و استفاده از این برنامه شما به یک صفحه کلید نیاز دارید.",
    "typing.showHands": "دستها را نمایش بده",
    "typing.hideHands": "دستها را پنهان کن",
    "typing.hand.left": "دست چپ",
    "typing.hand.right": "دست راست",
    "typing.finger.thumb": "شست",
    "typing.finger.index": "انگشت اشاره",
    "typing.finger.middle": "انگشت وسط",
    "typing.finger.ring": "انگشت حلقه",
    "typing.finger.little": "انگشت کوچک",
    "typing.hand.finger": "{hand} {finger}",
    "contribution.translate.title": "لطفاً در ترجمه صفحه کمک کنید",
    "contribution.translate.desc": "اگر به زبان انگلیسی (یا مجارستانی) مسلط می باشید، می توانید به دیگران کمک کنید تا از این برنامه به زبان مادری خود استفاده کنند. جزئیات بیشتری را در لینک زیر مشاهده می نمایید"
}
